gpucache/__init__.py
gpucache/advanced_multimodal_cache.py
gpucache/multimodal_cache_manager.py
gpucache/api/__init__.py
gpucache/api/app.py
gpucache/api/dashboard.py
gpucache/audio/__init__.py
gpucache/audio/audio_cache.py
gpucache/chats/__init__.py
gpucache/chats/core.py
gpucache/chats/disk.py
gpucache/chats/segment_cache.py
gpucache/cli/__init__.py
gpucache/cli/cli.py
gpucache/core/__init__.py
gpucache/core/adaptive_ttl_cache.py
gpucache/core/compression.py
gpucache/core/encryption.py
gpucache/core/export_manager.py
gpucache/core/hash.py
gpucache/core/kv_store.py
gpucache/core/metadata_store.py
gpucache/core/plugin_manager.py
gpucache/core/redis_store.py
gpucache/core/serializer.py
gpucache/core/token_prefill_cache.py
gpucache/core/vector_index.py
gpucache/normalizer/__init__.py
gpucache/normalizer/heavy_input_cache.py
gpucache/normalizer/semantic_input_cache.py
gpucache/rag/__init__.py
gpucache/rag/chunk_index.py
gpucache/tests/__init__.py
gpucache/tests/test_kv_backends.py
gpucache/tests/test_segment_cache.py
gpucache/tests/test_vector_index.py
gpucache/video/__init__.py
gpucache/video/video_cache.py
gpucache-0.2.2.dist-info/licenses/LICENSE
gpucache-0.2.2.dist-info/METADATA
gpucache-0.2.2.dist-info/WHEEL
gpucache-0.2.2.dist-info/entry_points.txt
gpucache-0.2.2.dist-info/top_level.txt
gpucache-0.2.2.dist-info/RECORD
