Metadata-Version: 2.4
Name: gpucache
Version: 0.2.2
Summary: Advanced Multimodal AI Cache System for GPU-optimized LLM deployments
Author-email: Prarabdha Soni <prarabdha.soni@gmail.com>
Keywords: cache,ai,vector,rag,audio,video,gpu,multimodal
Requires-Python: >=3.8
License-File: LICENSE
Requires-Dist: redis>=4.0
Requires-Dist: faiss-cpu
Requires-Dist: fastapi
Requires-Dist: uvicorn
Requires-Dist: numpy
Requires-Dist: aiohttp
Requires-Dist: pydantic
Requires-Dist: typer[all]
Requires-Dist: cryptography
Requires-Dist: pandas
Requires-Dist: pyarrow
Requires-Dist: psutil
Dynamic: license-file
